Metadata-Version: 2.1
Name: testit-importer-junit
Version: 1.2.5
Summary: Junit report importer for Test IT
Home-page: https://pypi.org/project/testit-importer-junit/
Author: Integration team
Author-email: integrations@testit.software
License: Apache-2.0
Classifier: Programming Language :: Python :: 3
Classifier: Programming Language :: Python :: 3.6
Classifier: Programming Language :: Python :: 3.7
Classifier: Programming Language :: Python :: 3.8
Classifier: Programming Language :: Python :: 3.9
